[
  {
    "event": "evaluate",
    "metrics": {
      "avg_loss": 2.5525179433608964,
      "round": 1
    }
  },
  {
    "event": "evaluate",
    "metrics": {
      "avg_loss": 1.612851424642758,
      "round": 2
    }
  },
  {
    "event": "evaluate",
    "metrics": {
      "avg_loss": 1.583969863461401,
      "round": 3
    }
  },
  {
    "event": "evaluate",
    "metrics": {
      "avg_loss": 1.1136620829104518,
      "round": 4
    }
  },
  {
    "event": "evaluate",
    "metrics": {
      "avg_loss": 1.0359983429730095
    }
  }
]